agent_runner/__init__.py
agent_runner/exceptions.py
agent_runner/logger.py
agent_runner/sdk.py
agent_runner/types.py
agent_runner/adapters/__init__.py
agent_runner/adapters/base.py
agent_runner/adapters/crewai_adapter.py
agent_runner/adapters/generic_adapter.py
agent_runner/adapters/langgraph_adapter.py
agent_runner/adapters/openai_adapter.py
agent_runner/streaming/__init__.py
agent_runner/streaming/normalizer.py
LICENSE
README.md
cli.py
templates/.env.template
templates/agent.yaml
templates/main.py
axen_runtime-0.2.6.dist-info/METADATA
axen_runtime-0.2.6.dist-info/WHEEL
axen_runtime-0.2.6.dist-info/entry_points.txt
axen_runtime-0.2.6.dist-info/licenses/LICENSE
axen_runtime-0.2.6.dist-info/RECORD
