Metadata-Version: 2.4
Name: axen-runtime
Version: 0.2.6
Summary: Universal runtime for AI agents - Deploy any agent with one line of code
Project-URL: Homepage, https://github.com/axen/runtime-app
Project-URL: Documentation, https://github.com/axen/runtime-app#readme
Project-URL: Repository, https://github.com/axen/runtime-app
Project-URL: Issues, https://github.com/axen/runtime-app/issues
Author-email: "AXEN INC." <dev@axen.run>
License-Expression: MIT
License-File: LICENSE
Keywords: agents,ai,crewai,deployment,langgraph,openai,runtime
Classifier: Development Status :: 3 - Alpha
Classifier: Intended Audience :: Developers
Classifier: License :: OSI Approved :: MIT License
Classifier: Programming Language :: Python :: 3
Classifier: Programming Language :: Python :: 3.10
Classifier: Programming Language :: Python :: 3.11
Classifier: Programming Language :: Python :: 3.12
Classifier: Topic :: Scientific/Engineering :: Artificial Intelligence
Classifier: Topic :: Software Development :: Libraries :: Python Modules
Requires-Python: >=3.10
Requires-Dist: pydantic>=2.5.0
Requires-Dist: python-dotenv>=1.0.0
Requires-Dist: typing-extensions>=4.9.0
Provides-Extra: all
Requires-Dist: crewai>=0.1.0; extra == 'all'
Requires-Dist: fastapi>=0.104.0; extra == 'all'
Requires-Dist: langchain-core>=0.1.10; extra == 'all'
Requires-Dist: langchain-openai>=0.0.2; extra == 'all'
Requires-Dist: langchain>=0.1.0; extra == 'all'
Requires-Dist: langgraph>=0.0.20; extra == 'all'
Requires-Dist: openai>=1.6.0; extra == 'all'
Requires-Dist: pydantic-settings>=2.1.0; extra == 'all'
Requires-Dist: pyyaml>=6.0; extra == 'all'
Requires-Dist: requests>=2.31.0; extra == 'all'
Requires-Dist: typer>=0.9.0; extra == 'all'
Requires-Dist: uvicorn[standard]>=0.24.0; extra == 'all'
Provides-Extra: cli
Requires-Dist: pyyaml>=6.0; extra == 'cli'
Requires-Dist: requests>=2.31.0; extra == 'cli'
Requires-Dist: typer>=0.9.0; extra == 'cli'
Provides-Extra: crewai
Requires-Dist: crewai>=0.1.0; extra == 'crewai'
Requires-Dist: langchain>=0.1.0; extra == 'crewai'
Provides-Extra: dev
Requires-Dist: black>=23.11.0; extra == 'dev'
Requires-Dist: mypy>=1.7.0; extra == 'dev'
Requires-Dist: pytest-asyncio>=0.21.0; extra == 'dev'
Requires-Dist: pytest>=7.4.0; extra == 'dev'
Requires-Dist: ruff>=0.1.0; extra == 'dev'
Provides-Extra: langchain
Requires-Dist: langchain-core>=0.1.10; extra == 'langchain'
Requires-Dist: langchain-openai>=0.0.2; extra == 'langchain'
Requires-Dist: langchain>=0.1.0; extra == 'langchain'
Provides-Extra: langgraph
Requires-Dist: langchain>=0.1.0; extra == 'langgraph'
Requires-Dist: langgraph>=0.0.20; extra == 'langgraph'
Provides-Extra: openai
Requires-Dist: openai>=1.6.1; extra == 'openai'
Provides-Extra: server
Requires-Dist: fastapi>=0.104.0; extra == 'server'
Requires-Dist: pydantic-settings>=2.1.0; extra == 'server'
Requires-Dist: python-dotenv>=1.0.0; extra == 'server'
Requires-Dist: python-multipart>=0.0.6; extra == 'server'
Requires-Dist: pyyaml>=6.0; extra == 'server'
Requires-Dist: uvicorn[standard]>=0.24.0; extra == 'server'
